amphipathic/__init__.py
amphipathic/secondary_structure.py
amphipathic/hydrophobic/__init__.py
amphipathic/hydrophobic/core.py
amphipathic/hydrophobic/cornette.py
amphipathic/hydrophobic/data/__init__.py
amphipathic/hydrophobic/data/cornette.csv
amphipathic/hydrophobic/data/cornette_normalized.csv
amphipathic-1.0.11.dist-info/AUTHORS
amphipathic-1.0.11.dist-info/LICENSE
amphipathic-1.0.11.dist-info/METADATA
amphipathic-1.0.11.dist-info/WHEEL
amphipathic-1.0.11.dist-info/top_level.txt
amphipathic-1.0.11.dist-info/zip-safe
amphipathic-1.0.11.dist-info/RECORD
