Metadata-Version: 2.1
Name: amphipathic
Version: 1.0.11
Summary: This is a library to evaluate an aminoacid sequence and determine an amphipathic index for each alpha helix or beta sheet.
Home-page: https://github.com/ecolell/amphipathic
Author: Eloy Adonis Colell
Author-email: eloy.colell@gmail.com
License: MIT
Platform: UNKNOWN
Classifier: Intended Audience :: Science/Research
Classifier: Programming Language :: Python
Classifier: Programming Language :: Python :: 3.6
Classifier: Topic :: Scientific/Engineering :: Bio-Informatics
Classifier: Topic :: Scientific/Engineering :: Information Analysis
Classifier: Topic :: Scientific/Engineering :: Physics
Requires-Dist: beautifulsoup4 (==4.6.3)
Requires-Dist: biopython
Requires-Dist: cachetools
Requires-Dist: ndg-httpsclient (==0.4.0)
Requires-Dist: pyOpenSSL (~=19.0.0)
Requires-Dist: pyasn1
Requires-Dist: requests[security]
